akrocansim/J1939DA.py
akrocansim/__init__.py
akrocansim/config.py
akrocansim/dbc.py
akrocansim/gui.py
akrocansim/signaltools.py
akrocansim/transmitter.py
akrocansim/version_check.py
akrocansim/resources/akrocansim.ico
akrocansim/resources/akrocansim_logo_dark.png
akrocansim-0.6.5.dist-info/METADATA
akrocansim-0.6.5.dist-info/WHEEL
akrocansim-0.6.5.dist-info/entry_points.txt
akrocansim-0.6.5.dist-info/licenses/LICENSE
akrocansim-0.6.5.dist-info/RECORD
