Metadata-Version: 2.4
Name: akrocansim
Version: 0.6.5
Dynamic: Summary
Project-URL: Home, https://github.com/cfsok/akrocansim
Author-email: pullthebox <socrates.vlassis@gmail.com>
License: MIT License
License-File: LICENSE
Keywords: CAN bus,J1939
Classifier: Development Status :: 4 - Beta
Classifier: License :: OSI Approved :: MIT License
Classifier: Programming Language :: Python :: 3.13
Classifier: Topic :: Software Development :: Embedded Systems
Classifier: Topic :: Software Development :: Embedded Systems :: Controller Area Network (CAN)
Classifier: Topic :: Software Development :: Embedded Systems :: Controller Area Network (CAN) :: J1939
Requires-Python: >=3.13
Requires-Dist: dearpygui==2.0.0
Requires-Dist: openpyxl==3.1.5
Requires-Dist: python-can==4.5.0
Requires-Dist: semver==3.0.4
